pelican/plugins/neighbors/__init__.py
pelican/plugins/neighbors/neighbors.py
pelican/plugins/neighbors/test_data/article.md
pelican/plugins/neighbors/test_neighbors.py
pelican_neighbors-1.1.0.dist-info/WHEEL
pelican_neighbors-1.1.0.dist-info/METADATA
pelican_neighbors-1.1.0.dist-info/RECORD
