Metadata-Version: 2.1
Name: pelican-neighbors
Version: 1.1.0
Summary: Neighbors is a Pelican plugin that adds Next/Previous links to articles
Home-page: https://github.com/pelican-plugins/neighbors
License: AGPL-3.0
Keywords: pelican,plugin,articles,navigation
Author: Justin Mayer
Author-email: entroP@gmail.com
Requires-Python: >=3.6,<4.0
Classifier: Development Status :: 5 - Production/Stable
Classifier: Environment :: Console
Classifier: Framework :: Pelican
Classifier: Framework :: Pelican :: Plugins
Classifier: Intended Audience :: End Users/Desktop
Classifier: License :: OSI Approved :: GNU Affero General Public License v3
Classifier: Operating System :: OS Independent
Classifier: Programming Language :: Python :: 3
Classifier: Programming Language :: Python :: 3.6
Classifier: Programming Language :: Python :: 3.7
Classifier: Programming Language :: Python :: 3.8
Classifier: Topic :: Internet :: WWW/HTTP
Classifier: Topic :: Software Development :: Libraries :: Python Modules
Provides-Extra: markdown
Requires-Dist: markdown (>=3.2.2,<4.0.0); extra == "markdown"
Requires-Dist: pelican (>=4.5,<5.0)
Project-URL: Documentation, https://docs.getpelican.com
Project-URL: Funding, https://donate.getpelican.com/
Project-URL: Issue Tracker, https://github.com/pelican-plugins/neighbors/issues
Project-URL: Repository, https://github.com/pelican-plugins/neighbors
